<?xml version="1.0" encoding="UTF-8"?>

<openbox_config xmlns="http://openbox.org/3.4/rc">
  <resistance>
    <strength>10</strength>
    <screen_edge_strength>20</screen_edge_strength>
  </resistance>
  <focus>
    <focusNew>yes</focusNew>
    <followMouse>no</followMouse>
    <focusLast>yes</focusLast>
    <underMouse>no</underMouse>
    <focusDelay>200</focusDelay>
    <raiseOnFocus>no</raiseOnFocus>
  </focus>
  <placement>
    <policy>Smart</policy>
    <center>yes</center>
    <monitor>Active</monitor>
    <primaryMonitor>1</primaryMonitor>
  </placement>
  <theme>
    <name>Onyx-Citrus</name>
    <titleLayout>NLIMC</titleLayout>
    <keepBorder>yes</keepBorder>
    <animateIconify>yes</animateIconify>
    <font place="ActiveWindow">
      <name>sans-serif</name>
      <size>10</size>
      <weight>Bold</weight>
      <slant>Normal</slant>
    </font>
    <font place="InactiveWindow">
      <name>sans-serif</name>
      <size>10</size>
      <weight>Bold</weight>
      <slant>Normal</slant>
    </font>
    <font place="MenuHeader">
      <name>sans-serif</name>
      <size>10</size>
      <weight>Normal</weight>
      <slant>Normal</slant>
    </font>
    <font place="MenuItem">
      <name>sans-serif</name>
      <size>10</size>
      <weight>Normal</weight>
      <slant>Normal</slant>
    </font>
    <font place="OnScreenDisplay">
      <name>sans-serif</name>
      <size>11</size>
      <weight>Bold</weight>
      <slant>Normal</slant>
    </font>
  </theme>
  <desktops>
    <number>2</number>
    <firstdesk>1</firstdesk>
    <names>
      <name>Primary</name>
      <name>Secondary</name>
    </names>
    <popupTime>875</popupTime>
  </desktops>
  <resize>
    <drawContents>yes</drawContents>
    <popupShow>Nonpixel</popupShow>
    <popupPosition>Center</popupPosition>
    <popupFixedPosition>
      <x>10</x>
      <y>10</y>
    </popupFixedPosition>
  </resize>
  <margins>
    <top>0</top>
    <bottom>0</bottom>
    <left>0</left>
    <right>0</right>
  </margins>
  <dock>
    <position>BottomLeft</position>
    <floatingX>0</floatingX>
    <floatingY>0</floatingY>
    <noStrut>no</noStrut>
    <stacking>Above</stacking>
    <direction>Vertical</direction>
    <autoHide>no</autoHide>
    <hideDelay>300</hideDelay>
    <showDelay>300</showDelay>
    <moveButton>Middle</moveButton>
  </dock>
  <keyboard>
    <chainQuitKey>C-g</chainQuitKey>
    <!-- Keybindings for desktop switching -->
    <keybind key="W-Left">
      <action name="DesktopLeft">
        <dialog>no</dialog>
        <wrap>no</wrap>
      </action>
    </keybind>
    <keybind key="W-Right">
      <action name="DesktopRight">
        <dialog>no</dialog>
        <wrap>no</wrap>
      </action>
    </keybind>
    <keybind key="W-Up">
      <action name="DesktopUp">
        <dialog>no</dialog>
        <wrap>no</wrap>
      </action>
    </keybind>
    <keybind key="W-Down">
      <action name="DesktopDown">
        <dialog>no</dialog>
        <wrap>no</wrap>
      </action>
    </keybind>
    <keybind key="W-A-Left">
      <action name="SendToDesktopLeft">
        <dialog>no</dialog>
        <wrap>no</wrap>
      </action>
    </keybind>
    <keybind key="W-A-Right">
      <action name="SendToDesktopRight">
        <dialog>no</dialog>
        <wrap>no</wrap>
      </action>
    </keybind>
    <keybind key="W-A-Up">
      <action name="SendToDesktopUp">
        <dialog>no</dialog>
        <wrap>no</wrap>
      </action>
    </keybind>
    <keybind key="W-A-Down">
      <action name="SendToDesktopDown">
        <dialog>no</dialog>
        <wrap>no</wrap>
      </action>
    </keybind>
    <keybind key="W-1">
      <action name="Desktop">
        <desktop>1</desktop>
      </action>
    </keybind>
    <keybind key="W-2">
      <action name="Desktop">
        <desktop>2</desktop>
      </action>
    </keybind>
    <keybind key="W-3">
      <action name="Desktop">
        <desktop>3</desktop>
      </action>
    </keybind>
    <keybind key="W-4">
      <action name="Desktop">
        <desktop>4</desktop>
      </action>
    </keybind>
    <keybind key="W-d">
      <action name="ToggleShowDesktop"/>
    </keybind>
    <!-- Keybindings for windows -->
    <keybind key="A-F4">
      <action name="Close"/>
    </keybind>
    <keybind key="A-F11">
      <action name="ToggleFullscreen"/>
    </keybind>
    <keybind key="A-space">
      <action name="ShowMenu">
        <menu>client-menu</menu>
      </action>
    </keybind>
    <!-- Keybindings for window switching -->
    <keybind key="A-Tab">
      <action name="NextWindow"/>
    </keybind>
    <keybind key="A-S-Tab">
      <action name="PreviousWindow"/>
    </keybind>
    <keybind key="W-Tab">
      <action name="NextWindow">
        <allDesktops>yes</allDesktops>
      </action>
    </keybind>
    <!-- Keybindings for displaying menus -->
    <keybind key="W-Escape">
      <action name="ShowMenu">
        <menu>root-menu</menu>
      </action>
    </keybind>
    <!-- Keybindings for running applications -->
    <keybind key="W-r">
      <action name="Execute">
        <command>gmrun</command>
      </action>
    </keybind>
    <keybind key="C-S-Escape">
      <action name="Execute">
        <command>lxtask</command>
      </action>
    </keybind>
  </keyboard>
  <mouse>
    <dragThreshold>8</dragThreshold>
    <doubleClickTime>200</doubleClickTime>
    <screenEdgeWarpTime>400</screenEdgeWarpTime>
    <context name="Frame">
      <mousebind button="A-Left" action="Press">
        <action name="Focus"/>
        <action name="Raise"/>
      </mousebind>
      <mousebind button="A-Left" action="Click">
        <action name="Unshade"/>
      </mousebind>
      <mousebind button="A-Left" action="Drag">
        <action name="Move"/>
      </mousebind>
      <mousebind button="A-Right" action="Press">
        <action name="Focus"/>
        <action name="Raise"/>
        <action name="Unshade"/>
      </mousebind>
      <mousebind button="A-Right" action="Drag">
        <action name="Resize"/>
      </mousebind>
      <mousebind button="A-Middle" action="Press">
        <action name="Lower"/>
        <action name="FocusToBottom"/>
        <action name="Unfocus"/>
      </mousebind>
    </context>
    <context name="Titlebar">
      <mousebind button="Left" action="Press">
        <action name="Focus"/>
        <action name="Raise"/>
      </mousebind>
      <mousebind button="Left" action="Drag">
        <action name="Move"/>
      </mousebind>
      <mousebind button="Left" action="DoubleClick">
        <action name="ToggleMaximizeFull"/>
      </mousebind>
      <mousebind button="Middle" action="Press">
        <action name="Lower"/>
        <action name="FocusToBottom"/>
        <action name="Unfocus"/>
      </mousebind>
      <mousebind button="Up" action="Click">
        <action name="Shade"/>
        <action name="FocusToBottom"/>
        <action name="Unfocus"/>
        <action name="Lower"/>
      </mousebind>
      <mousebind button="Down" action="Click">
        <action name="Unshade"/>
        <action name="Raise"/>
      </mousebind>
      <mousebind button="Right" action="Press">
        <action name="Focus"/>
        <action name="Raise"/>
        <action name="ShowMenu">
          <menu>client-menu</menu>
        </action>
      </mousebind>
    </context>
    <context name="Top">
      <mousebind button="Left" action="Press">
        <action name="Focus"/>
        <action name="Raise"/>
        <action name="Unshade"/>
      </mousebind>
      <mousebind button="Left" action="Drag">
        <action name="Resize">
          <edge>top</edge>
        </action>
      </mousebind>
    </context>
    <context name="Left">
      <mousebind button="Left" action="Press">
        <action name="Focus"/>
        <action name="Raise"/>
      </mousebind>
      <mousebind button="Left" action="Drag">
        <action name="Resize">
          <edge>left</edge>
        </action>
      </mousebind>
      <mousebind button="Right" action="Press">
        <action name="Focus"/>
        <action name="Raise"/>
        <action name="ShowMenu">
          <menu>client-menu</menu>
        </action>
      </mousebind>
    </context>
    <context name="Right">
      <mousebind button="Left" action="Press">
        <action name="Focus"/>
        <action name="Raise"/>
      </mousebind>
      <mousebind button="Left" action="Drag">
        <action name="Resize">
          <edge>right</edge>
        </action>
      </mousebind>
      <mousebind button="Right" action="Press">
        <action name="Focus"/>
        <action name="Raise"/>
        <action name="ShowMenu">
          <menu>client-menu</menu>
        </action>
      </mousebind>
    </context>
    <context name="Bottom">
      <mousebind button="Left" action="Press">
        <action name="Focus"/>
        <action name="Raise"/>
      </mousebind>
      <mousebind button="Left" action="Drag">
        <action name="Resize">
          <edge>bottom</edge>
        </action>
      </mousebind>
      <mousebind button="Middle" action="Press">
        <action name="Lower"/>
        <action name="FocusToBottom"/>
        <action name="Unfocus"/>
      </mousebind>
      <mousebind button="Right" action="Press">
        <action name="Focus"/>
        <action name="Raise"/>
        <action name="ShowMenu">
          <menu>client-menu</menu>
        </action>
      </mousebind>
    </context>
    <context name="BLCorner">
      <mousebind button="Left" action="Press">
        <action name="Focus"/>
        <action name="Raise"/>
      </mousebind>
      <mousebind button="Left" action="Drag">
        <action name="Resize"/>
      </mousebind>
    </context>
    <context name="BRCorner">
      <mousebind button="Left" action="Press">
        <action name="Focus"/>
        <action name="Raise"/>
      </mousebind>
      <mousebind button="Left" action="Drag">
        <action name="Resize"/>
      </mousebind>
    </context>
    <context name="TLCorner">
      <mousebind button="Left" action="Press">
        <action name="Focus"/>
        <action name="Raise"/>
        <action name="Unshade"/>
      </mousebind>
      <mousebind button="Left" action="Drag">
        <action name="Resize"/>
      </mousebind>
    </context>
    <context name="TRCorner">
      <mousebind button="Left" action="Press">
        <action name="Focus"/>
        <action name="Raise"/>
        <action name="Unshade"/>
      </mousebind>
      <mousebind button="Left" action="Drag">
        <action name="Resize"/>
      </mousebind>
    </context>
    <context name="Client">
      <mousebind button="Left" action="Press">
        <action name="Focus"/>
        <action name="Raise"/>
      </mousebind>
      <mousebind button="Middle" action="Press">
        <action name="Focus"/>
        <action name="Raise"/>
      </mousebind>
      <mousebind button="Right" action="Press">
        <action name="Focus"/>
        <action name="Raise"/>
      </mousebind>
    </context>
    <context name="Icon">
      <mousebind button="Left" action="Press">
        <action name="Focus"/>
        <action name="Raise"/>
        <action name="Unshade"/>
        <action name="ShowMenu">
          <menu>client-menu</menu>
        </action>
      </mousebind>
      <mousebind button="Right" action="Press">
        <action name="Focus"/>
        <action name="Raise"/>
        <action name="ShowMenu">
          <menu>client-menu</menu>
        </action>
      </mousebind>
    </context>
    <context name="AllDesktops">
      <mousebind button="Left" action="Press">
        <action name="Focus"/>
        <action name="Raise"/>
        <action name="Unshade"/>
      </mousebind>
      <mousebind button="Left" action="Click">
        <action name="ToggleOmnipresent"/>
      </mousebind>
    </context>
    <context name="Shade">
      <mousebind button="Left" action="Press">
        <action name="Focus"/>
        <action name="Raise"/>
      </mousebind>
      <mousebind button="Left" action="Click">
        <action name="ToggleShade"/>
      </mousebind>
    </context>
    <context name="Iconify">
      <mousebind button="Left" action="Press">
        <action name="Focus"/>
        <action name="Raise"/>
      </mousebind>
      <mousebind button="Left" action="Click">
        <action name="Iconify"/>
      </mousebind>
    </context>
    <context name="Maximize">
      <mousebind button="Left" action="Press">
        <action name="Focus"/>
        <action name="Raise"/>
        <action name="Unshade"/>
      </mousebind>
      <mousebind button="Middle" action="Press">
        <action name="Focus"/>
        <action name="Raise"/>
        <action name="Unshade"/>
      </mousebind>
      <mousebind button="Right" action="Press">
        <action name="Focus"/>
        <action name="Raise"/>
        <action name="Unshade"/>
      </mousebind>
      <mousebind button="Left" action="Click">
        <action name="ToggleMaximizeFull"/>
      </mousebind>
      <mousebind button="Middle" action="Click">
        <action name="ToggleMaximizeVert"/>
      </mousebind>
      <mousebind button="Right" action="Click">
        <action name="ToggleMaximizeHorz"/>
      </mousebind>
    </context>
    <context name="Close">
      <mousebind button="Left" action="Press">
        <action name="Focus"/>
        <action name="Raise"/>
        <action name="Unshade"/>
      </mousebind>
      <mousebind button="Left" action="Click">
        <action name="Close"/>
      </mousebind>
    </context>
    <context name="Desktop">
      <mousebind button="Left" action="Press">
        <action name="Focus"/>
        <action name="Raise"/>
      </mousebind>
      <mousebind button="Right" action="Press">
        <action name="Focus"/>
        <action name="Raise"/>
      </mousebind>
    </context>
    <context name="Root">
      <mousebind button="Middle" action="Press">
        <action name="ShowMenu">
          <menu>client-list-combined-menu</menu>
        </action>
      </mousebind>
      <mousebind button="Right" action="Press">
        <action name="ShowMenu">
          <menu>root-menu</menu>
        </action>
      </mousebind>
    </context>
    <context name="MoveResize">
    </context>
  </mouse>
  <menu>
    <file>menu.xml</file>
    <hideDelay>200</hideDelay>
    <middle>no</middle>
    <submenuShowDelay>100</submenuShowDelay>
    <submenuHideDelay>400</submenuHideDelay>
    <applicationIcons>yes</applicationIcons>
    <manageDesktops>yes</manageDesktops>
  </menu>
  <applications>
  </applications>
</openbox_config>
